foundry_manager/__init__.py
foundry_manager/asset_manager.py
foundry_manager/asset_processor.py
foundry_manager/cli.py
foundry_manager/cli_output.py
foundry_manager/config.py
foundry_manager/docker_manager.py
foundry_manager/foundry_instance_manager.py
foundry_manager/foundry_versions.py
foundry_manager/game_system_manager.py
foundry_manager/instance_record_manager.py
foundry_manager/module_manager.py
foundry_manager/world_manager.py
foundry_instance_manager-0.1.32.dist-info/LICENSE
foundry_instance_manager-0.1.32.dist-info/METADATA
foundry_instance_manager-0.1.32.dist-info/WHEEL
foundry_instance_manager-0.1.32.dist-info/entry_points.txt
foundry_instance_manager-0.1.32.dist-info/RECORD
